tableqallmagent/__init__.py
tableqallmagent/agent.py
tableqallmagent/code_manipulation.py
tableqallmagent/coder_llms.py
tableqallmagent/llms.py
tableqallmagent/logger.py
tableqallmagent/prompts.py
tableqallmagent-0.1.14.dist-info/METADATA
tableqallmagent-0.1.14.dist-info/WHEEL
tableqallmagent-0.1.14.dist-info/RECORD
