Metadata-Version: 2.1
Name: tableqallmagent
Version: 0.1.14
Summary: 
Author: poludmik
Author-email: michael.poludin@gmail.com
Requires-Python: >=3.9,<3.13
Classifier: Programming Language :: Python :: 3
Classifier: Programming Language :: Python :: 3.9
Classifier: Programming Language :: Python :: 3.10
Classifier: Programming Language :: Python :: 3.11
Classifier: Programming Language :: Python :: 3.12
Requires-Dist: autopep8 (>=2.0.4,<3.0.0)
Requires-Dist: deprecated (>=1.2.14,<2.0.0)
Requires-Dist: langchain (==0.1.17)
Requires-Dist: langchain-anthropic (>=0.1.11,<0.2.0)
Requires-Dist: langsmith (==0.1.53)
Requires-Dist: matplotlib (>=3.8.1,<4.0.0)
Requires-Dist: numpy (>=1.26.2,<2.0.0)
Requires-Dist: openai (>=1.3.2,<2.0.0)
Requires-Dist: openpyxl (>=3.1.2,<4.0.0)
Requires-Dist: pandas (>=2.1.3,<3.0.0)
Requires-Dist: peft (>=0.10.0,<0.11.0)
Requires-Dist: pytest (>=8.1.1,<9.0.0)
Requires-Dist: scikit-learn (>=1.3.2,<2.0.0)
Requires-Dist: scipy (>=1.11.3,<2.0.0)
Requires-Dist: torch (>=2.2.2,<3.0.0)
Requires-Dist: transformers (>=4.39.3,<5.0.0)
